<vehicles xmlns:xsi="http://www.w3.org/2001/XMLSchema-instance" xmlns:xsd="http://www.w3.org/2001/XMLSchema" route_id="230" route_name="230" route_type="3" mode_name="Bus"><direction direction_id="0" direction_name="Outbound"><trip trip_id="24952126" trip_name="6:00 pm from Quincy Center Bus Station to Montello Commuter Rail Station" trip_headsign="Montello via Braintree Station"><vehicle vehicle_id="y0777" vehicle_lat="42.1198768615723" vehicle_lon="-71.0170288085938" vehicle_timestamp="1418860558" /></trip><trip trip_id="24952101" trip_name="6:30 pm from Quincy Center Bus Station to Montello Commuter Rail Station" trip_headsign="Montello via Braintree Station"><vehicle vehicle_id="y0758" vehicle_lat="42.2275886535645" vehicle_lon="-71.0049438476563" vehicle_timestamp="1418860543" /></trip></direction><direction direction_id="1" direction_name="Inbound"><trip trip_id="24952149" trip_name="6:28 pm from Montello Commuter Rail Station to Quincy Center Bus Station" trip_headsign="Quincy Center Station via Braintree Station"><vehicle vehicle_id="y0791" vehicle_lat="42.1926422119141" vehicle_lon="-71.0062789916992" vehicle_timestamp="1418860530" /></trip></direction></vehicles>