<vehicles xmlns:xsi="http://www.w3.org/2001/XMLSchema-instance" xmlns:xsd="http://www.w3.org/2001/XMLSchema" route_id="230" route_name="230" route_type="3" mode_name="Bus"><direction direction_id="0" direction_name="Outbound"><trip trip_id="24951971" trip_name="3:00 pm from Quincy Center Bus Station to Montello Commuter Rail Station" trip_headsign="Montello via Linwood Housing"><vehicle vehicle_id="y0787" vehicle_lat="42.1812782287598" vehicle_lon="-71.0138473510742" vehicle_timestamp="1418848839" /></trip><trip trip_id="24952144" trip_name="3:30 pm from Quincy Center Bus Station to Montello Commuter Rail Station" trip_headsign="Montello via Braintree Station"><vehicle vehicle_id="y0905" vehicle_lat="42.2414245605469" vehicle_lon="-71.0035171508789" vehicle_timestamp="1418848833" /></trip></direction><direction direction_id="1" direction_name="Inbound"><trip trip_id="24951865" trip_name="3:17 pm from Montello Commuter Rail Station to Quincy Center Bus Station" trip_headsign="Quincy Center Station via Linwood Housing"><vehicle vehicle_id="y0791" vehicle_lat="42.2077484130859" vehicle_lon="-71.0037155151367" vehicle_timestamp="1418848810" /></trip></direction></vehicles>